roland_piano/__init__.py
roland_piano/roland_address_map.py
roland_piano/roland_instruments.py
roland_piano/roland_messages.py
roland_piano/roland_piano.py
roland_piano/roland_utils.py
roland_piano-0.4.0.dist-info/LICENSE
roland_piano-0.4.0.dist-info/METADATA
roland_piano-0.4.0.dist-info/WHEEL
roland_piano-0.4.0.dist-info/top_level.txt
roland_piano-0.4.0.dist-info/RECORD
