Metadata-Version: 2.1
Name: roland-piano
Version: 0.4.0
Summary: A library to interface with Roland FP pianos over midi
Home-page: https://github.com/evanraalte/RolandPiano
Author: Erik van Raalte
Author-email: erik.vanraalte94@gmail.com
Project-URL: Bug Tracker, https://github.com/evanraalte/RolandPiano/issues
Classifier: Programming Language :: Python :: 3
Classifier: License :: OSI Approved :: MIT License
Classifier: Operating System :: OS Independent
Requires-Python: >=3.7
License-File: LICENSE
Requires-Dist: mido
Requires-Dist: python-rtmidi
